karrio/mappers/bpost/__init__.py
karrio/mappers/bpost/mapper.py
karrio/mappers/bpost/proxy.py
karrio/mappers/bpost/settings.py
karrio/plugins/bpost/__init__.py
karrio/providers/bpost/__init__.py
karrio/providers/bpost/error.py
karrio/providers/bpost/tracking.py
karrio/providers/bpost/units.py
karrio/providers/bpost/utils.py
karrio/providers/bpost/shipment/__init__.py
karrio/providers/bpost/shipment/cancel.py
karrio/providers/bpost/shipment/create.py
karrio/schemas/bpost/__init__.py
karrio/schemas/bpost/announcement_common_v1.py
karrio/schemas/bpost/business_exception.py
karrio/schemas/bpost/common_v5.py
karrio/schemas/bpost/international_v5.py
karrio/schemas/bpost/national_v5.py
karrio/schemas/bpost/shm_deep_integration_v5.py
karrio/schemas/bpost/system_exception.py
karrio/schemas/bpost/tracking_info_v1.py
karrio_bpost-2026.1.4.dist-info/METADATA
karrio_bpost-2026.1.4.dist-info/WHEEL
karrio_bpost-2026.1.4.dist-info/entry_points.txt
karrio_bpost-2026.1.4.dist-info/top_level.txt
karrio_bpost-2026.1.4.dist-info/RECORD
